<?xml version="1.0" encoding="utf-8"?>
<odoo>
  <data>

    <!-- ═══════════════════════════════════════════════════════
         LAYOUT — Age gate + lightbox container

         These are injected once at the top of every page via
         website.layout's wrapwrap anchor — a stable element
         present in every header/footer variant. Both are hidden
         by default (CSS .hidden / JS-controlled), so they have
         zero visual impact until activated by age_gate.js /
         ratings.js.
    ════════════════════════════════════════════════════════ -->
    <template id="layout_additions" inherit_id="website.layout" name="Cellar One Layout Additions">
      <xpath expr="//div[@id='wrapwrap']" position="before">

        <!-- Age Gate -->
        <div id="co-age-gate" class="co-age-gate hidden">
          <div class="co-age-gate__backdrop"></div>
          <div class="co-age-gate__modal">
            <div class="co-age-gate__header">
              <div class="co-age-gate-logo">Cellar <span>One</span></div>
              <div class="co-age-gate-icon">🍷</div>
              <h2>Welcome to Cellar One</h2>
              <p>Uganda's premier wines &amp; spirits destination</p>
            </div>
            <div class="co-age-gate__body">
              <p class="co-age-gate-question">Are you 18 years of age or older?</p>
              <div class="co-age-gate-actions">
                <button class="co-age-yes">Yes, I am 18+</button>
                <button class="co-age-no">No, I am not</button>
              </div>
              <p class="co-age-gate-legal">
                By entering this site you agree to our
                <a href="/terms">Terms of Service</a> and
                <a href="/privacy">Privacy Policy</a>.
                Please drink responsibly.
              </p>
            </div>
            <div class="co-age-gate__denied">
              <div class="co-denied-icon">🚫</div>
              <h3>Access Restricted</h3>
              <p>Sorry, you must be 18 or older to access this website. Redirecting…</p>
            </div>
          </div>
        </div>

        <!-- Lightbox (used by product gallery hover/zoom, ratings.js) -->
        <div id="co-lightbox" class="co-lightbox">
          <img class="co-lightbox__img" src="" alt="Product image"/>
          <button class="co-lightbox__close" aria-label="Close">✕</button>
        </div>

      </xpath>
    </template>


    <!-- ═══════════════════════════════════════════════════════
         NAVBAR — WhatsApp quick-order CTA

         Stable anchor: #o_main_nav is the real container id inside
         website.template_header_default (confirmed in source). We
         append a WhatsApp button after the brand/menu block, inside
         the existing nav row, rather than replacing any part of the
         navbar's login/search/account markup (which is wired to
         portal session JS we should not disturb).
    ════════════════════════════════════════════════════════ -->
    <template id="navbar_whatsapp_cta"
              inherit_id="website.template_header_default"
              name="Cellar One Navbar WhatsApp CTA">
      <xpath expr="//div[@id='o_main_nav']" position="inside">
        <a href="https://wa.me/256749057433" target="_blank" rel="noopener"
           class="btn-co-nav-cta d-none d-xl-inline-flex align-items-center gap-1 ms-2 order-last">
          <i class="fa fa-whatsapp"/> Order via WhatsApp
        </a>
      </xpath>
    </template>

  </data>
</odoo>
